.gitignore
LICENSE
README.md
requirements.txt
setup.cfg
setup.py
caelus/__init__.py
caelus.egg-info/PKG-INFO
caelus.egg-info/SOURCES.txt
caelus.egg-info/dependency_links.txt
caelus.egg-info/requires.txt
caelus.egg-info/top_level.txt
caelus/aws/__init__.py
caelus/aws/auth/__init__.py
caelus/aws/auth/aws_auth.py
caelus/aws/storages/__init__.py
caelus/aws/storages/s3_storage.py
caelus/aws/users/__init__.py
caelus/aws/users/aws_identity.py
caelus/aws/users/aws_security.py
caelus/aws/utils/__init__.py
caelus/aws/utils/utils.py
caelus/az/__init__.py
caelus/az/auth/__init__.py
caelus/az/auth/azure_auth.py
caelus/az/storages/__init__.py
caelus/az/storages/blob_storage.py
caelus/core/__init__.py
caelus/core/utils.py
caelus/core/storages/__init__.py
caelus/core/storages/storage.py
caelus/gcp/__init__.py
caelus/gcp/auth/__init__.py
caelus/gcp/auth/gcp_auth.py
caelus/gcp/storages/__init__.py
caelus/gcp/storages/cloud_storage.py
tutorial/image.jpeg
tutorial/aws/S3Storage-test.py
tutorial/azure/BlobStorage-test.py
tutorial/google-cloud/CloudStorage-test.py